MANIFEST.in
README.rst
requirements.txt
setup.cfg
setup.py
sentinel_s3/__init__.py
sentinel_s3/converter.py
sentinel_s3/crawler.py
sentinel_s3/main.py
sentinel_s3.egg-info/PKG-INFO
sentinel_s3.egg-info/SOURCES.txt
sentinel_s3.egg-info/dependency_links.txt
sentinel_s3.egg-info/requires.txt
sentinel_s3.egg-info/top_level.txt