Metadata-Version: 1.1
Name: sentinel-s3
Version: 0.7.0
Summary: Python libraries for extracting Sentinel-2's metadata from Amazon S3
Home-page: https://github.com/developmentseed/sentinel-s3
Author: Alireza J (scisco)
Author-email: alireza@developmentseed.org
License: CC0
Download-URL: https://github.com/developmentseed/sentinel-s3/tarball/0.7.0
Platform: UNKNOWN
Classifier: Framework :: Pytest
Classifier: Topic :: Scientific/Engineering :: GIS
Classifier: Topic :: Scientific/Engineering
Classifier: Intended Audience :: Developers
Classifier: Intended Audience :: Science/Research
Classifier: License :: Freeware
Classifier: Programming Language :: Python :: 2.7
Classifier: Programming Language :: Python :: 3.3
Classifier: Programming Language :: Python :: 3.4
Classifier: Programming Language :: Python :: 3.5
